threading_futures/__init__.py
threading_futures/errors.py
threading_futures/exceptions.py
threading_futures/futures.py
threading_futures-1.0.dist-info/DESCRIPTION.rst
threading_futures-1.0.dist-info/METADATA
threading_futures-1.0.dist-info/RECORD
threading_futures-1.0.dist-info/WHEEL
threading_futures-1.0.dist-info/metadata.json
threading_futures-1.0.dist-info/top_level.txt
