Metadata-Version: 2.0
Name: threading-futures
Version: 1.0
Summary: Python Threading Futures
Home-page: https://github.com/MichalJagiello/threading_futures
Author: Michal Jagiello
Author-email: michal.jagiello@hotmail.com
License: MIT
Keywords: threading futures
Platform: UNKNOWN
